treescript_builder/__init__.py
treescript_builder/__main__.py
treescript_builder/data/__init__.py
treescript_builder/data/data_directory.py
treescript_builder/data/instruction_data.py
treescript_builder/data/path_stack.py
treescript_builder/data/tree_data.py
treescript_builder/data/tree_state.py
treescript_builder/input/__init__.py
treescript_builder/input/argument_data.py
treescript_builder/input/argument_parser.py
treescript_builder/input/file_validation.py
treescript_builder/input/input_data.py
treescript_builder/input/line_reader.py
treescript_builder/input/string_validation.py
treescript_builder/tree/__init__.py
treescript_builder/tree/build_validation.py
treescript_builder/tree/tree_builder.py
treescript_builder/tree/tree_trimmer.py
treescript_builder/tree/trim_validation.py
treescript_builder-0.1.12.dist-info/licenses/LICENSE
treescript_builder-0.1.12.dist-info/METADATA
treescript_builder-0.1.12.dist-info/WHEEL
treescript_builder-0.1.12.dist-info/entry_points.txt
treescript_builder-0.1.12.dist-info/top_level.txt
treescript_builder-0.1.12.dist-info/RECORD
