Metadata-Version: 2.4
Name: treescript-builder
Version: 0.1.12
Summary: Builds File Trees from TreeScript. If DataLabels are present in TreeScript, a DataDirectory argument is required.
Home-page: https://github.com/DK96-OS/treescript-builder
Author: DK96-OS
License: GPLv3
Project-URL: Issues, https://github.com/DK96-OS/treescript-builder/issues
Project-URL: Source Code, https://github.com/DK96-OS/treescript-builder
Keywords: TreeScript,Files,Directory
Classifier: Natural Language :: English
Classifier: Operating System :: OS Independent
Classifier: Intended Audience :: Developers
Classifier: License :: OSI Approved :: GNU General Public License v3 (GPLv3)
Classifier: Programming Language :: Python :: 3
Classifier: Programming Language :: Python :: 3.11
Classifier: Programming Language :: Python :: 3.12
Classifier: Programming Language :: Python :: 3.13
Classifier: Programming Language :: Python :: 3.14
Requires-Python: >=3.11
License-File: LICENSE
Dynamic: author
Dynamic: classifier
Dynamic: description
Dynamic: description-content-type
Dynamic: home-page
Dynamic: keywords
Dynamic: license
Dynamic: license-file
Dynamic: project-url
Dynamic: requires-python
Dynamic: summary
